MANIFEST.in
README.txt
setup.py
docs/HISTORY.txt
src/silva/__init__.py
src/silva.security.renameusers.egg-info/PKG-INFO
src/silva.security.renameusers.egg-info/SOURCES.txt
src/silva.security.renameusers.egg-info/dependency_links.txt
src/silva.security.renameusers.egg-info/namespace_packages.txt
src/silva.security.renameusers.egg-info/not-zip-safe
src/silva.security.renameusers.egg-info/requires.txt
src/silva.security.renameusers.egg-info/top_level.txt
src/silva/security/__init__.py
src/silva/security/renameusers/__init__.py
src/silva/security/renameusers/configure.zcml
src/silva/security/renameusers/ftesting.zcml
src/silva/security/renameusers/rename.py
src/silva/security/renameusers/testing.py
src/silva/security/renameusers/tests/__init__.py
src/silva/security/renameusers/tests/test_rename.py
src/silva/security/renameusers/tests/data/renames.csv