Metadata-Version: 1.1
Name: silva.security.renameusers
Version: 1.0
Summary: Rename users identifier in a Silva site
Home-page: https://github.com/silvacms/silva.security.renameusers
Author: Infrae
Author-email: info@infrae.com
License: BSD
Keywords: silva cms zope security rename users
Platform: UNKNOWN
Classifier: Framework :: Zope2
Classifier: License :: OSI Approved :: BSD License
Classifier: Programming Language :: Python
Classifier: Topic :: Software Development :: Libraries :: Python Modules
